tidal_stability/__init__.py
tidal_stability/__version__.py
tidal_stability/physics_constants.py
tidal_stability/utils.py
tidal_stability/data_formats/__init__.py
tidal_stability/data_formats/_containers.py
tidal_stability/data_formats/_dumpers.py
tidal_stability/data_formats/_loaders.py
tidal_stability/solve/__init__.py
tidal_stability/solve/deriv_funcs.py
tidal_stability/solve/geometry.py
tidal_stability/solve/solution.py
tidal_stability/solve/utils.py
tidal_stability-1.0.12.dist-info/LICENSE.md
tidal_stability-1.0.12.dist-info/METADATA
tidal_stability-1.0.12.dist-info/WHEEL
tidal_stability-1.0.12.dist-info/top_level.txt
tidal_stability-1.0.12.dist-info/RECORD
